{
  "schema": {
    "type": "object",
    "properties": {
      "$$data": {
        "type": "object",
        "default": ""
      },
      "$$espace": {
        "title": "espace 信息配置",
        "type": "array",
        "default": ""
      },
      "popper-append-to-body": {
        "title": "是否将弹出框插入至 body 元素。在弹出框的定位出现问题时，可将该属性设置为 false (可参考 select 组件)",
        "type": "boolean",
        "default": true
      },
      "$$popper-class": {
        "title": "为 popper 添加类名(可参考 popover 组件)",
        "type": "string",
        "default": ""
      },
      "show-img": {
        "title": "是否显示头像",
        "type": "boolean",
        "default": true
      },
      "show-name": {
        "title": "是否显示姓名 userName",
        "type": "boolean",
        "default": true
      },
      "show-number": {
        "title": "是否显示工号 roleNumber",
        "type": "boolean",
        "default": true
      },
      "#default": {
        "title": "默认插槽",
        "type": "string"
      }
    }
  }
}
